isaacgym-stubs/__init__.py
isaacgym-stubs/gymapi.pyi
isaacgym_stubs-1.1rc4.dist-info/LICENSE
isaacgym_stubs-1.1rc4.dist-info/METADATA
isaacgym_stubs-1.1rc4.dist-info/WHEEL
isaacgym_stubs-1.1rc4.dist-info/top_level.txt
isaacgym_stubs-1.1rc4.dist-info/RECORD
