Metadata-Version: 2.1
Name: isaacgym-stubs
Version: 1.1rc4
Summary: Isaac Gym Python Stubs for Code Completion
Author: Yuzhe Qin
Author-email: Yuzhe Qin <y1qin@ucsd.edu>
Project-URL: Homepage, https://github.com/yzqin/isaacgym-stubs
Classifier: Programming Language :: Python :: 3
Classifier: License :: OSI Approved :: MIT License
Classifier: Operating System :: OS Independent
Requires-Python: >=3.6
License-File: LICENSE
